cleanrl/c51.py
cleanrl/c51_atari.py
cleanrl/c51_atari_jax.py
cleanrl/c51_jax.py
cleanrl/ddpg_continuous_action.py
cleanrl/ddpg_continuous_action_jax.py
cleanrl/dqn.py
cleanrl/dqn_atari.py
cleanrl/dqn_atari_impalacnn.py
cleanrl/dqn_atari_jax.py
cleanrl/dqn_atari_jax_impalacnn.py
cleanrl/dqn_jax.py
cleanrl/old.py
cleanrl/ppg_procgen.py
cleanrl/ppo.py
cleanrl/ppo_atari.py
cleanrl/ppo_atari_envpool.py
cleanrl/ppo_atari_envpool_async_jax_scan_impalanet_machado.py
cleanrl/ppo_atari_envpool_impala.py
cleanrl/ppo_atari_envpool_xla_jax.py
cleanrl/ppo_atari_envpool_xla_jax_scan.py
cleanrl/ppo_atari_lstm.py
cleanrl/ppo_atari_multigpu.py
cleanrl/ppo_continuous_action.py
cleanrl/ppo_continuous_action_isaacgym/isaacgym/poetry.lock
cleanrl/ppo_continuous_action_isaacgym/isaacgym/pyproject.toml
cleanrl/ppo_continuous_action_isaacgym/ppo_continuous_action_isaacgym.py
cleanrl/ppo_pettingzoo_ma_atari.py
cleanrl/ppo_procgen.py
cleanrl/ppo_rnd_envpool.py
cleanrl/qdagger_dqn_atari.py
cleanrl/qdagger_dqn_atari_impalacnn.py
cleanrl/qdagger_dqn_atari_jax_impalacnn.py
cleanrl/runs/Breakout-v5__ppo_atari_envpool_async_jax_scan_impalanet_machado__1__1672537248/events.out.tfevents.1672537248.pop-os
cleanrl/runs/Breakout-v5__ppo_atari_envpool_async_jax_scan_impalanet_machado__1__1672537272/README.md
cleanrl/runs/Breakout-v5__ppo_atari_envpool_async_jax_scan_impalanet_machado__1__1672537272/events.out.tfevents.1672537272.pop-os
cleanrl/runs/Breakout-v5__ppo_atari_envpool_async_jax_scan_impalanet_machado__1__1672537272/ppo_atari_envpool_async_jax_scan_impalanet_machado.cleanrl_model
cleanrl/runs/Pong-v5__ppo_atari_envpool_xla_jax_scan__1__1672522293/events.out.tfevents.1672522293.pop-os.723498.0
cleanrl/runs/Pong-v5__ppo_atari_envpool_xla_jax_scan__1__1672522402/events.out.tfevents.1672522402.pop-os.726144.0
cleanrl/runs/Pong-v5__ppo_atari_envpool_xla_jax_scan__1__1672522402/ppo_atari_envpool_xla_jax_scan.cleanrl_model
cleanrl/runs/Pong-v5__ppo_atari_envpool_xla_jax_scan__1__1672522486/README.md
cleanrl_test-1.1.2.dist-info/METADATA
cleanrl_test-1.1.2.dist-info/WHEEL
cleanrl_test-1.1.2.dist-info/LICENSE
cleanrl_test-1.1.2.dist-info/RECORD
