Metadata-Version: 2.1
Name: cleanrl-test
Version: 1.1.2
Summary: High-quality single file implementation of Deep Reinforcement Learning algorithms with research-friendly features
License: MIT
Keywords: reinforcement,machine,learning,research
Author: Costa Huang
Author-email: costa.huang@outlook.com
Requires-Python: >=3.7.1,<3.10
Classifier: License :: OSI Approved :: MIT License
Classifier: Programming Language :: Python :: 3
Classifier: Programming Language :: Python :: 3.8
Classifier: Programming Language :: Python :: 3.9
Provides-Extra: atari
Provides-Extra: c51
Provides-Extra: c51-atari
Provides-Extra: c51-atari-jax
Provides-Extra: c51-jax
Provides-Extra: cloud
Provides-Extra: dm-control
Provides-Extra: docs
Provides-Extra: dqn
Provides-Extra: dqn-atari
Provides-Extra: dqn-atari-jax
Provides-Extra: dqn-jax
Provides-Extra: envpool
Provides-Extra: jax
Provides-Extra: mujoco
Provides-Extra: mujoco-py
Provides-Extra: optuna
Provides-Extra: pettingzoo
Provides-Extra: plot
Provides-Extra: ppo-atari-envpool-xla-jax-scan
Provides-Extra: procgen
Provides-Extra: pybullet
Provides-Extra: pytest
Requires-Dist: AutoROM[accept-rom-license] (>=0.4.2,<0.5.0) ; extra == "atari" or extra == "dqn-atari" or extra == "dqn-atari-jax" or extra == "c51-atari" or extra == "c51-atari-jax" or extra == "ppo-atari-envpool-xla-jax-scan"
Requires-Dist: PettingZoo (==1.18.1) ; extra == "pettingzoo"
Requires-Dist: SuperSuit (==3.4.0) ; extra == "pettingzoo"
Requires-Dist: ale-py (==0.7.4) ; extra == "atari" or extra == "dqn-atari" or extra == "dqn-atari-jax" or extra == "c51-atari" or extra == "c51-atari-jax" or extra == "ppo-atari-envpool-xla-jax-scan"
Requires-Dist: awscli (>=1.25.71,<2.0.0) ; extra == "cloud"
Requires-Dist: boto3 (>=1.24.70,<2.0.0) ; extra == "cloud"
Requires-Dist: dm-control (>=1.0.8,<2.0.0) ; extra == "dm-control"
Requires-Dist: envpool (>=0.7.1,<0.8.0) ; extra == "envpool" or extra == "ppo-atari-envpool-xla-jax-scan"
Requires-Dist: flax (>=0.6.0,<0.7.0) ; extra == "jax" or extra == "dqn-jax" or extra == "dqn-atari-jax" or extra == "c51-jax" or extra == "c51-atari-jax" or extra == "ppo-atari-envpool-xla-jax-scan"
Requires-Dist: free-mujoco-py (>=2.1.6,<3.0.0) ; extra == "mujoco-py"
Requires-Dist: gym (==0.23.1)
Requires-Dist: gymnasium (>=0.26.3,<0.27.0)
Requires-Dist: huggingface-hub (>=0.11.1,<0.12.0)
Requires-Dist: imageio (>=2.14.1,<3.0.0) ; extra == "mujoco"
Requires-Dist: jax (>=0.3.17,<0.4.0) ; extra == "jax" or extra == "dqn-jax" or extra == "dqn-atari-jax" or extra == "c51-jax" or extra == "c51-atari-jax" or extra == "ppo-atari-envpool-xla-jax-scan"
Requires-Dist: jaxlib (>=0.3.15,<0.4.0) ; extra == "jax" or extra == "dqn-jax" or extra == "dqn-atari-jax" or extra == "c51-jax" or extra == "c51-atari-jax" or extra == "ppo-atari-envpool-xla-jax-scan"
Requires-Dist: markdown-include (>=0.7.0,<0.8.0) ; extra == "docs"
Requires-Dist: mkdocs-material (>=8.4.3,<9.0.0) ; extra == "docs"
Requires-Dist: moviepy (>=1.0.3,<2.0.0)
Requires-Dist: mujoco (>=2.2,<3.0) ; extra == "mujoco" or extra == "dm-control"
Requires-Dist: multi-agent-ale-py (==0.1.11) ; extra == "pettingzoo"
Requires-Dist: opencv-python (>=4.6.0.66,<5.0.0.0) ; extra == "atari" or extra == "dqn-atari" or extra == "dqn-atari-jax" or extra == "c51-atari" or extra == "c51-atari-jax" or extra == "ppo-atari-envpool-xla-jax-scan"
Requires-Dist: optuna (>=3.0.1,<4.0.0) ; extra == "optuna"
Requires-Dist: optuna-dashboard (>=0.7.2,<0.8.0) ; extra == "optuna"
Requires-Dist: procgen (>=0.10.7,<0.11.0) ; extra == "procgen"
Requires-Dist: pybullet (==3.1.8) ; extra == "pybullet"
Requires-Dist: pygame (==2.1.0)
Requires-Dist: pytest (>=7.1.3,<8.0.0) ; extra == "pytest"
Requires-Dist: rich (<12.0) ; extra == "optuna"
Requires-Dist: shimmy (>=0.1.0,<0.2.0) ; extra == "dm-control"
Requires-Dist: stable-baselines3 (==1.2.0)
Requires-Dist: tensorboard (>=2.10.0,<3.0.0)
Requires-Dist: torch (>=1.12.1)
Requires-Dist: wandb (>=0.13.6,<0.14.0)
